stis_number/__init__.py
stis_number/_version.py
stis_number/is_number.py
stis_number-0.0.7.dist-info/LICENSE
stis_number-0.0.7.dist-info/METADATA
stis_number-0.0.7.dist-info/WHEEL
stis_number-0.0.7.dist-info/top_level.txt
stis_number-0.0.7.dist-info/RECORD
